comm_methods/__init__.py
comm_methods/applescript_comm.py
comm_methods/gdb_communicator.py
comm_methods/keyboard_comm.py
comm_methods/pexpect_comm.py
mseep_gdb_mcp_server-0.2.2.dist-info/licenses/LICENSE
mseep_gdb_mcp_server-0.2.2.dist-info/METADATA
mseep_gdb_mcp_server-0.2.2.dist-info/WHEEL
mseep_gdb_mcp_server-0.2.2.dist-info/top_level.txt
mseep_gdb_mcp_server-0.2.2.dist-info/RECORD
