Metadata-Version: 2.4
Name: mseep-gdb-mcp-server
Version: 0.2.2
Summary: GDB Model Context Protocol Server for AI-assisted debugging
Home-page: 
Author: mseep
Author-email: mseep <support@skydeck.ai>
Maintainer-email: mseep <support@skydeck.ai>
Requires-Python: >=3.6
License-File: LICENSE
Requires-Dist: fastmcp>=0.1.0
Requires-Dist: pexpect>=4.8.0
Provides-Extra: windows
Requires-Dist: pyautogui>=0.9.50; extra == "windows"
Provides-Extra: dev
Requires-Dist: black; extra == "dev"
Requires-Dist: isort; extra == "dev"
Requires-Dist: mypy; extra == "dev"
Dynamic: author
Dynamic: license-file
Dynamic: requires-python
